README.txt
setup.cfg
setup.py
docs/AUTHORS.txt
docs/CHANGES.txt
docs/INSTALL.txt
docs/LICENSE.txt
p4a/__init__.py
p4a.ploneaudio.egg-info/PKG-INFO
p4a.ploneaudio.egg-info/SOURCES.txt
p4a.ploneaudio.egg-info/dependency_links.txt
p4a.ploneaudio.egg-info/entry_points.txt
p4a.ploneaudio.egg-info/namespace_packages.txt
p4a.ploneaudio.egg-info/not-zip-safe
p4a.ploneaudio.egg-info/requires.txt
p4a.ploneaudio.egg-info/top_level.txt
p4a/ploneaudio/__init__.py
p4a/ploneaudio/atct.py
p4a/ploneaudio/atct.txt
p4a/ploneaudio/browser.txt
p4a/ploneaudio/configure.zcml
p4a/ploneaudio/content.py
p4a/ploneaudio/indexing.py
p4a/ploneaudio/indexing.txt
p4a/ploneaudio/plone-audio-impl.txt
p4a/ploneaudio/plone-audio.txt
p4a/ploneaudio/sitesetup.py
p4a/ploneaudio/sitesetup.txt
p4a/ploneaudio/syndication-integration.txt
p4a/ploneaudio/syndication.py
p4a/ploneaudio/syndication.txt
p4a/ploneaudio/syndication.zcml
p4a/ploneaudio/ataudio/__init__.py
p4a/ploneaudio/ataudio/ataudiotests.py
p4a/ploneaudio/ataudio/browser.py
p4a/ploneaudio/ataudio/configure.zcml
p4a/ploneaudio/ataudio/interfaces.py
p4a/ploneaudio/ataudio/migrate-ataudio-configlet.pt
p4a/ploneaudio/ataudio/migration.py
p4a/ploneaudio/ataudio/migration.txt
p4a/ploneaudio/profiles/default/actions.xml
p4a/ploneaudio/tests/__init__.py
p4a/ploneaudio/tests/test_functional.py
p4a/ploneaudio/tests/test_unit.py
p4a/ploneaudio/tests/testing.py
