Metadata-Version: 1.0
Name: p4a.ploneaudio
Version: 1.0.1
Summary: Plone4Artists audio add-on for Plone 
Home-page: http://www.plone4artists.org/products/plone4artistsaudio
Author: Rocky Burt
Author-email: rocky@serverzen.com
License: GPL
Keywords: Plone4Artists
Platform: UNKNOWN
Classifier: Framework :: Zope3
Classifier: Framework :: Plone
Classifier: Programming Language :: Python
Classifier: License :: OSI Approved :: GNU General Public License (GPL)
Classifier: Topic :: Software Development :: Libraries :: Python Modules
Classifier: Topic :: Multimedia :: Sound/Audio
